hi_haramss/__init__.py
hi_haramss/hello.py
hi_HaramSS-0.8.0.dist-info/METADATA
hi_HaramSS-0.8.0.dist-info/WHEEL
hi_HaramSS-0.8.0.dist-info/entry_points.txt
hi_HaramSS-0.8.0.dist-info/top_level.txt
hi_HaramSS-0.8.0.dist-info/RECORD
